<innhold>
    <avsnitt type="element">Etter at du har søkt</avsnitt>
    <avsnitt>Du kan logge deg inn på <lenke url="https://foreldrepenger.nav.no" ekstern="true">Ditt NAV</lenke>, og sjå status i saka di. Her kan du også ettersende vedlegg.</avsnitt>
    <avsnitt>Dersom du har søkt på papirskjema, kan du sjå status i saka di etter omkring 10 dagar.</avsnitt>
    <avsnitt>Saksbehandlingstida er vanlegvis inntil 6 veker. <lenke url="https://www.nav.no/no/nav-og-samfunn/om-nav/saksbehandlingstider-i-nav" ekstern="true">Sjå kva saksbehandlingstiden er i fylket ditt</lenke></avsnitt>
    <avsnitt type="element">Utbetalinger</avsnitt>
    <avsnitt>Du får vanlegvis utbetalt eingongsstønaden éi veke etter at søknaden din er innvilga. Eingongsstønaden er skattefri. Du kan logge deg inn på Ditt NAV og <lenke url="https://tjenester.nav.no/dittnav/oversikt" ekstern="true">sjå utbetalingane</lenke> du har fått dei siste tre åra.</avsnitt>
</innhold>