<innhold>
    <liste>
        <punkt>I <b>foreldrepengesøknaden</b> legger du inn perioden du skal ha foreldrepenger fordi den andre forelderen er syk.</punkt>
        <punkt>Hvis du <b>allerede har søkt</b>, logger du på <lenke url="https://foreldrepenger.nav.no/" ekstern="true">Dine foreldrepenger</lenke> og sender en endringssøknad i isteden.</punkt>
    </liste>
    <avsnitt type="element">Dette må du legge ved søknaden</avsnitt>
    <liste>
        <punkt>Den andre forelderen er <b>syk, men hjemme</b>: Legg ved en legeerklæring. Legen må beskrive konkret på hvilken måte sykdommen eller skaden gjør den andre forelderen helt avhengig av hjelp til å ta deg av barnet. Det vil si hvilke deler av stellet av barnet den andre forelderen ikke kan gjøre på grunn av sykdommen eller skaden. Det må også stå hvor lenge sykdommen eller skaden vil vare. Det er ikke nok med vanlig sykmelding.</punkt>
        <punkt>Den andre forelderen er <b>innlagt</b>: Legg ved dokumentasjon fra helseinstitusjonen på periode for innleggelse.</punkt>
    </liste>
    <avsnitt><b>Søkefrist</b>: Du må søke innen 3 måneder.</avsnitt>
</innhold>