<innhold>
    <avsnitt class="blokk-xxs">In connection with <b>adoption</b>, you cannot apply for parental benefit until you have a date <b>for assumption of care</b>.</avsnitt>
    <avsnitt>The <b>latest</b> you can apply is 3 months after the date for assumption of care. If you apply at a later date, you will be granted fewer days of parental benefit.</avsnitt>
    <avsnitt>If you adopt from abroad, you can choose if you would like to start receiving the parental benefit when you assume care of the child while abroad, or the day you arrive in Norway with the child. The latest you can apply is 3 months after the date for assumption of care/arrival in Norway. If you apply later, you will be granted fewer days of parental benefit.</avsnitt>
</innhold>