<innhold>
    <avsnitt>Foreldrepengeperioden din starter senest <b>3 uker</b> før terminen. Du kan velge å starte så tidlig som 12 uker før, men da får du færre uker etter fødselen.</avsnitt>
    <avsnitt>Adopterer du, starter foreldrepengeperioden din ved <b>omsorgsovertakelse.</b></avsnitt>
    <avsnitt>Ved adopsjon fra utlandet kan du velge om du vil begynne å ta ut foreldrepengene når du overtar omsorgen for barnet i utlandet, eller den dagen du kommer til Norge sammen med barnet.</avsnitt>
    <avsnitt>Les mer om hele <lenke url="https://familie.nav.no/om-foreldrepenger" ekstern="false">søknadsprosessen.</lenke></avsnitt>
</innhold>